gitignore/__init__.py
gitignore/__main__.py
gitignore/ignore.py
git_autoignore-1.0.4.dist-info/METADATA
git_autoignore-1.0.4.dist-info/WHEEL
git_autoignore-1.0.4.dist-info/entry_points.txt
git_autoignore-1.0.4.dist-info/top_level.txt
git_autoignore-1.0.4.dist-info/RECORD
