Metadata-Version: 2.1
Name: git-autoignore
Version: 1.0.4
Summary: Create gitignore template with lighten Speed
Home-page: https://github.com/Imdeepmehta/git-autoignore
Author: Imdeepmehta
Author-email: itsdeepmehta25@gmail.com
License: MIT
Platform: UNKNOWN
Requires-Dist: requests
Requires-Dist: beautifulsoup4
Requires-Dist: lxml
